voca/__init__.py
voca/voca.py
voca_gorae-0.0.2.dist-info/METADATA
voca_gorae-0.0.2.dist-info/WHEEL
voca_gorae-0.0.2.dist-info/entry_points.txt
voca_gorae-0.0.2.dist-info/top_level.txt
voca_gorae-0.0.2.dist-info/RECORD
