Metadata-Version: 2.1
Name: voca-gorae
Version: 0.0.2
Summary: A printable vocabulary exam generator for Amgigore
Home-page: https://github.com/BetaF1sh/voca
Author: Muhun Kim
Author-email: iam@muhun.kim
License: MIT
Keywords: printable,vocabulary,exam,generator
Platform: UNKNOWN
Classifier: Environment :: Console
Classifier: Programming Language :: Python :: 3
Classifier: Programming Language :: Python :: 3.3
Classifier: Programming Language :: Python :: 3.4
Classifier: Programming Language :: Python :: 3.5
Classifier: Programming Language :: Python :: 3.6
Requires-Dist: pandas
Requires-Dist: flask
